<?xml version="1.0"?>
<configuration>

  <property>
    <name>dfs.nameservices</name>
    <value>test_cluster</value>
  </property>
  <property>
    <name>dfs.ha.namenodes.test_cluster</name>
    <value>nn1,nn2</value>
  </property>
  <property>
    <name>dfs.namenode.rpc-address.test_cluster.nn1</name>
    <value>namenode1:9000</value>
  </property>
  <property>
    <name>dfs.namenode.rpc-address.test_cluster.nn2</name>
    <value>namenode2:9000</value>
  </property>
  <property>
    <name>dfs.namenode.http-address.test_cluster.nn1</name>
    <value>namenode1:9870</value>
  </property>
  <property>
    <name>dfs.namenode.http-address.test_cluster.nn2</name>
    <value>namenode2:9870</value>
  </property>
  <property>
    <name>dfs.client.failover.proxy.provider.test_cluster</name>
    <value>org.apache.hadoop.hdfs.server.namenode.ha.ConfiguredFailoverProxyProvider</value>
  </property>
  <property>
    <name>dfs.ha.automatic-failover.enabled</name>
    <value>true</value>
  </property>
  <property>
    <name>dfs.ha.fencing.methods</name>
    <value>shell(/bin/true)</value>
  </property>

  <property>
    <name>dfs.journalnode.edits.dir</name>
    <value>/hadoop/dfs/journal</value>
  </property>
  <property>
    <name>dfs.namenode.shared.edits.dir</name>
    <value>qjournal://journalnode1:8485;journalnode2:8485;journalnode3:8485/test_cluster</value>
  </property>

  <property>
    <name>ha.zookeeper.quorum</name>
    <value>zookeeper1:2181,zookeeper2:2181,zookeeper3:2181</value>
  </property>

  <property>
    <name>dfs.replication</name>
    <value>3</value>
  </property>

</configuration>
